mt940parser-0.0.2.dist-info/METADATA
mt940parser-0.0.2.dist-info/top_level.txt
mt940parser-0.0.2.dist-info/zip-safe
mt940parser-0.0.2.dist-info/WHEEL
mt940parser-0.0.2.dist-info/RECORD
mt940parser-0.0.2.dist-info/metadata.json
mt940parser-0.0.2.dist-info/DESCRIPTION.rst
mt940_tests/test_parse_actual_data.py
mt940_tests/test_parser.py
mt940_tests/parsetab.py
mt940_tests/__init__.py
mt940_tests/test_fields.py
mt940/fields.py
mt940/__init__.py
mt940/parser.py
