Metadata-Version: 2.0
Name: mt940parser
Version: 0.0.2
Summary: MT940 / MT942 message parser implemented as a context-free grammar in PLY.
Home-page: https://github.com/salimfadhley/mt940
Author: Salim Fadhley
Author-email: salimfadhley@gmail.com
License: MIT
Platform: UNKNOWN
Classifier: Development Status :: 2 - Pre-Alpha
Classifier: Environment :: Console
Classifier: Intended Audience :: Developers
Classifier: License :: OSI Approved :: MIT License
Classifier: Natural Language :: English
Classifier: Operating System :: OS Independent
Classifier: Programming Language :: Python :: 2.7
Classifier: Programming Language :: Python :: 3
Classifier: Topic :: Software Development :: Testing
Requires-Dist: ply
